[
  {
    "photo1": "https://upload.wikimedia.org/wikipedia/en/thumb/7/74/Hamilton_Honey_Badgers_Logo.png/250px-Hamilton_Honey_Badgers_Logo.png",
    "name1": "Sj Honey Badgers",
    "photo2": "https://encrypted-tbn0.gstatic.com/images?q=tbn:ANd9GcSs7qNxJ96C4SG7NEdRUlLoM80kzHTQ2bpNLlXhCVkn2A&s=10",
    "name2": "Chuggernauts",
    "champ": "Hockey sur glace. USA. UAHL",
    "heure": "00H00",
    "date": "07/07/2026",
    "pro": "V2"
  },
  {
    "photo1": "https://png.pngtree.com/png-vector/20241011/ourmid/pngtree-gladiator-spartan-logo-vector-png-image_14013939.png",
    "name1": "Gladiators UAHL",
    "photo2": "https://encrypted-tbn0.gstatic.com/images?q=tbn:ANd9GcQxaCGWGrmGTrG5r4tyV1zIB7gH8jTMYUHUQyxLJN4bXQ&s=10",
    "name2": "Malty Ducks",
    "champ": "Hockey sur glace. USA. UAHL",
    "heure": "00H10",
    "date": "07/07/2026",
    "pro": "Handicap: 2(0)"
  },
  {
    "photo1": "https://images.seeklogo.com/logo-png/47/1/chill-logo-png_seeklogo-470228.png",
    "name1": "Chill UAHL",
    "photo2": "https://encrypted-tbn0.gstatic.com/images?q=tbn:ANd9GcT388n_9wY5a2Zaun8uZoAGcvSoWwt0usrsnaygS5qN7otS7EnjvpxqmNxG&s=10",
    "name2": "Rockets UAHL",
    "champ": "Hockey sur glace. USA. UAHL",
    "heure": "01H35",
    "date": "07/07/2026",
    "pro": "Total: (+7.5)"
  },
    {
    "photo1": "https://upload.wikimedia.org/wikipedia/commons/1/14/Tampa-Bay-Rays-Logo-2008-2018-700x394.png",
    "name1": "Tampa Bay Rays",
    "photo2": "https://upload.wikimedia.org/wikipedia/commons/3/35/Yankees_logo.png",
    "name2": "Yankees de New York",
    "champ": "Baseball. États-Unis. MLB",
    "heure": "22H40",
    "date": "06/07/2026",
    "pro": "Handicap: 1(3)"
  },
    {
    "photo1": "https://encrypted-tbn0.gstatic.com/images?q=tbn:ANd9GcRV3rEujG2rT5yUwFVN8BOACluojz38X-zAHVAugFOb6w&s=10",
    "name1": "Washington Nationals",
    "photo2": "https://encrypted-tbn0.gstatic.com/images?q=tbn:ANd9GcTHM9t8Ar7ucpofQ8Cl-MNHmeazquEi1eJBEOl_WrTIYQ&s=10",
    "name2": "Astros de Houston",
    "champ": "Baseball. États-Unis. MLB",
    "heure": "22H45",
    "date": "06/07/2026",
    "pro": "Total: (+8)"
  },
   {
    "photo1": "https://upload.wikimedia.org/wikipedia/fr/e/ee/St_LouisCardinals.png",
    "name1": "Cardinals de Saint-Louis",
    "photo2": "https://upload.wikimedia.org/wikipedia/fr/a/ab/Brewers_de_Milwaukee_2020.png",
    "name2": "Brewers de Milwaukee",
    "champ": "Baseball. États-Unis. MLB",
    "heure": "23H45",
    "date": "06/07/2026",
    "pro": "Total: (+6)"
  }
]
